README.md
setup.py
aidedp_nlp/__init__.py
aidedp_nlp.egg-info/PKG-INFO
aidedp_nlp.egg-info/SOURCES.txt
aidedp_nlp.egg-info/dependency_links.txt
aidedp_nlp.egg-info/requires.txt
aidedp_nlp.egg-info/top_level.txt
aidedp_nlp/law/__init__.py
aidedp_nlp/law/process_data_law.py
aidedp_nlp/law/qwen_lora_merge.py
aidedp_nlp/law/说明.py
aidedp_nlp/mrpc/__init__.py
aidedp_nlp/mrpc/create_dataset.py
aidedp_nlp/mrpc/predict1.8.py
aidedp_nlp/mrpc/test1.5.py
aidedp_nlp/mrpc/test1.8.py
aidedp_nlp/mrpc/train1.5.py
aidedp_nlp/mrpc/train1.8.py
aidedp_nlp/mrpc/说明.py
aidedp_nlp/rte/__init__.py
aidedp_nlp/upload/1.pypirc.py
aidedp_nlp/upload/ChatGLM3.pdf.py
aidedp_nlp/upload/__init__.py
aidedp_nlp/upload/ch.py
aidedp_nlp/upload/setup.py